main.py
api/__init__.py
api/schemas.py
api/routes/devices_routes.py
api/routes/scenarios_routes.py
automation/__init__.py
automation/actions.py
automation/scenarios.py
automation/triggers.py
core/__init__.py
core/event_system.py
core/hub.py
db/__init__.py
db/models.py
db/repository.py
db/session.py
services/__init__.py
services/device_service.py
services/event_service.py
services/scenario_service.py
tests/conftest.py
tests/test_devices.py
tests/test_performance_base.py
tests/test_performance_devices.py
tests/test_performance_scenarios.py
tests/test_scenarios.py
smart_home_artur-1.0.4.dist-info/METADATA
smart_home_artur-1.0.4.dist-info/WHEEL
smart_home_artur-1.0.4.dist-info/top_level.txt
smart_home_artur-1.0.4.dist-info/RECORD
