Metadata-Version: 2.4
Name: smart-home-artur
Version: 1.0.4
Summary: Умный Дом
Author-email: Arthur <evdokimmarutan@gmail.com>
Project-URL: Homepage, https://github.com/arturmarutyan/smart_house
Project-URL: Repository, https://github.com/arturmarutyan/smart_house
Requires-Python: >=3.12
Requires-Dist: fastapi
Requires-Dist: uvicorn
Requires-Dist: psycopg2-binary
Requires-Dist: sqlalchemy
Requires-Dist: pydantic
Requires-Dist: pydantic_settings
Requires-Dist: asyncpg
Requires-Dist: alembic
Requires-Dist: build
Requires-Dist: wheel
Requires-Dist: pytest
Requires-Dist: pytest-asyncio
Requires-Dist: pytest-cov
Requires-Dist: pytest-benchmark
Requires-Dist: httpx
